CHANGES.txt
README.txt
setup.py
src/plone/__init__.py
src/plone.recipe.distros.egg-info/PKG-INFO
src/plone.recipe.distros.egg-info/SOURCES.txt
src/plone.recipe.distros.egg-info/dependency_links.txt
src/plone.recipe.distros.egg-info/entry_points.txt
src/plone.recipe.distros.egg-info/namespace_packages.txt
src/plone.recipe.distros.egg-info/requires.txt
src/plone.recipe.distros.egg-info/top_level.txt
src/plone/recipe/__init__.py
src/plone/recipe/distros/__init__.py
