Metadata-Version: 1.0
Name: plone.recipe.distros
Version: 1.3
Summary: ZC Buildout recipe for installing distributions.
Home-page: http://svn.plone.org/svn/collective/buildout/plone.recipe.distros
Author: Hanno Schlichting
Author-email: plone@hannosch.info
License: ZPL 2.1
Keywords: buildout
Platform: UNKNOWN
Classifier: License :: OSI Approved :: Zope Public License
Classifier: Framework :: Plone
Classifier: Framework :: Buildout
Classifier: Programming Language :: Python
